{"title":"코스모폴리탄 코리아 ─ 셀레브리티","url":"https://www.cosmopolitan.co.kr/celebs","favicon":"https://www.cosmopolitan.co.kr/favicon.ico","elements":[{"title":"차은우의 그녀, 인디아 아이슬리는 누구?","contents":"올리비아 핫세 딸다운 미모 자랑 중.","link":"https://www.cosmopolitan.co.kr/article/84041","retrieved":1706840167912},{"title":"고음 폭발 '레베카' 부를 때 옥주현의 속마음은?!","contents":"사실은 인간미 넘치는 댄버스 부인","link":"https://www.cosmopolitan.co.kr/article/84036","retrieved":1706800151730},{"title":"뷔 ♥️ 아이유 하고 싶은 거 다한 ‘럽윈올’ 뮤비","contents":"그 동안 쌓은 인복 이 앨범에 다 썼다!","link":"https://www.cosmopolitan.co.kr/article/84032","retrieved":1706753991425},{"title":"꿈은 이루어진다! 한소희·유재석 드디어 성덕되다?","contents":"엄마, 나 드디어 덕계못 탈출했어!","link":"https://www.cosmopolitan.co.kr/article/84005","retrieved":1706692145667},{"title":"아시안컵 16강 경기 일정! 한국은 누구와 언제?","contents":"대한민국 파이팅!","link":"https://www.cosmopolitan.co.kr/article/84004","retrieved":1706692145668},{"title":"이제 제발 그만해. 김재중·정은지가 팬에게 경고한 이유?","contents":"자택 방문부터 편지, 택시까지?!","link":"https://www.cosmopolitan.co.kr/article/84002","retrieved":1706692145669},{"title":"인생은 즐거워! 멋쁨의 인간화 모니카의 무반주 댄스?","contents":"풀버전은 코스모폴리탄 유튜브에서.","link":"https://www.cosmopolitan.co.kr/article/83998","retrieved":1706681513567},{"title":"물+덱스=극락, 믿고 보는 물덱스 모음집","contents":"귀엽고 멋지고 아주 다해버리는 덱스.","link":"https://www.cosmopolitan.co.kr/article/83997","retrieved":1706670601009}]}