{"title":"코스모폴리탄 코리아 ─ 셀레브리티","url":"https://www.cosmopolitan.co.kr/celebs","favicon":"https://www.cosmopolitan.co.kr/favicon_cosmo.ico?v=20190812","elements":[{"title":"차예련 ♥ 주상욱, 올해로 6년차 부부의 달~달한 럽스타 근황!","contents":"이런게 바로 찐사랑~.","link":"https://www.cosmopolitan.co.kr/article/62877","retrieved":1641968220697,"image":"https://image.jtbcplus.kr/data/contents/jam_photo/202201/11/bd80a404-b5e1-4087-bde9-f54cdf1c5183.jpg"},{"title":"배우 강예원, <솔로지옥> 송지아의 매니저로 전환?","contents":"&lt;전참시&gt; 에서 어떤 모습으로 등장할지 주목!","link":"https://www.cosmopolitan.co.kr/article/62876","retrieved":1641968220697,"image":"https://image.jtbcplus.kr/data/contents/jam_photo/202201/11/aa5a4098-e1d0-4636-872a-1e1f72fca7f9.jpg"},{"title":"본캐 연예인 부캐 화가인 솔비∙송민호∙하정우∙하지원∙박기웅 이들이 궁금하다면?","contents":"투잡러? 아니구 아트테이너~!","link":"https://www.cosmopolitan.co.kr/article/62874","retrieved":1641957178722,"image":"https://image.jtbcplus.kr/data/contents/jam_photo/202201/11/edd0e35f-3aa0-448d-80e0-eb3181cf929e.jpg"},{"title":"방탄까지 킹정한 ‘스걸파’ 댄서들의 찐 젠지 룩이 궁금해?","contents":"방탄소년단 RM, 정국의 애정공세로 종영 후에도 열기가 식지 않는 스걸파 앓이~ BTS의 마...","link":"https://www.cosmopolitan.co.kr/article/62873","retrieved":1641888839168,"image":"https://image.jtbcplus.kr/data/contents/jam_photo/202201/11/2319ec99-b9a5-480f-be9d-180a0ebc5458.jpg"},{"title":"최애가 왜 여기서 나와?! 예상치 못하게 뉴스에 등장한 연예인 모음.zip","contents":"뉴스를 뒤집어 놓은 아이돌, 래퍼, 배우의 정체는?!","link":"https://www.cosmopolitan.co.kr/article/62867","retrieved":1641885023848,"image":"https://image.jtbcplus.kr/data/contents/jam_photo/202201/11/ae4b8a6b-3cfb-495c-b956-e2481a642fa4.jpg"},{"title":"안재현∙송강∙정해인, 완깐머리 하고 순둥이 이미지 탈피한 남배우들?!","contents":"덮머리vs깐머리, 앞머리 따라 온도 차이 확 나는 천의 얼굴들","link":"https://www.cosmopolitan.co.kr/article/62866","retrieved":1641881791043,"image":"https://image.jtbcplus.kr/data/contents/jam_photo/202201/11/7c7b55d9-9de3-409e-8400-0f51408820f5.jpg"},{"title":"김나영♥마이큐 커플 패션 탐구! 사랑스러운 패피 둘의 만남","contents":"옷장까지 공유하는 사이?","link":"https://www.cosmopolitan.co.kr/article/62865","retrieved":1641881791046,"image":"https://image.jtbcplus.kr/data/contents/jam_photo/202201/11/e660af21-acac-476d-88ca-17f276aaa96a.jpg"},{"title":"눈에서 꿀이 뚝뚝!<솔로지옥>∙<돌싱글즈2>등 지금 가장 달달한 커플4","contents":"얘들아 잘 봐, 언니들 연애다!","link":"https://www.cosmopolitan.co.kr/article/62847","retrieved":1641881791049,"image":"https://image.jtbcplus.kr/data/contents/jam_photo/202201/11/a78d8c5c-9c2e-4615-b453-02e38bb5c565.jpg"}]}