{"title":"코스모폴리탄 코리아 ─ 셀레브리티","url":"https://www.cosmopolitan.co.kr/celebs","favicon":"https://www.cosmopolitan.co.kr/favicon_cosmo.ico?v=20190812","elements":[{"title":"킷캣 밸런타인 보이 등장! 이번 밸런타인데이를 더 달콤하게 만들어줄 주인공은?","contents":"킷캣의 NEW 신제품, 하트 틴 케이스를 들고 있는 주인공 곧 공개! 많관BOO!","link":"https://www.cosmopolitan.co.kr/article/63668","retrieved":1644307969463,"image":"https://image.jtbcplus.kr/data/contents/jam_photo/202202/08/a4908d5e-c35a-4f95-bf87-5b07c674192f.jpg"},{"title":"“매주가 레전드!” 놀토 분장에 진심인듯한 태연 착장 모음ZIP","contents":"소화력 무엇?!~ 분장 유형별로 보는 태연의 콘셉트 소화력!","link":"https://www.cosmopolitan.co.kr/article/63643","retrieved":1644304230111,"image":"https://image.jtbcplus.kr/data/contents/jam_photo/202202/07/4e9382c9-de60-4949-bb08-cca2af05dbb4.jpg"},{"title":"송혜교, 넷플릭스 오리지널 <더 글로리>로 차기작 결정","contents":"김은숙 작가의 차기작으로 이도현, 신예은, 임지현, 박성훈도 함께할 예정!","link":"https://www.cosmopolitan.co.kr/article/63641","retrieved":1644304230113,"image":"https://image.jtbcplus.kr/data/contents/jam_photo/202202/07/642c128b-13f5-4b23-b453-933628be87f2.jpg"},{"title":"달걀 흰자 먹는 데 2분 30초? 키∙안소희∙코쿤 소식좌들의 식사법","contents":"달걀 흰자 먹는 데 2분 30초? 키, 안소희, 코쿤 소식좌들의 식사법","link":"https://www.cosmopolitan.co.kr/article/63638","retrieved":1644300742757,"image":"https://image.jtbcplus.kr/data/contents/jam_photo/202202/07/c2a3e4df-31d1-4c4b-bb12-5d3956783c71.jpg"},{"title":"'지우학' 주인공, 벌써부터 다음 작품 기대 중?","contents":"현재까지 넷플릭스 TV쇼 부분 글로벌 1위 기록을 이어가고 있는 지우학의 주인공들! 로몬, ...","link":"https://www.cosmopolitan.co.kr/article/63635","retrieved":1644300742765,"image":"https://image.jtbcplus.kr/data/contents/jam_photo/202202/07/57a11b8d-0bae-4dd4-b788-7d614b4ac675.jpg"},{"title":"타고난 막냉이 재질! 최우식∙공명∙나인우∙로몬","contents":"오늘부터 내 이상형은 막냉이들.","link":"https://www.cosmopolitan.co.kr/article/63632","retrieved":1644296920823,"image":"https://image.jtbcplus.kr/data/contents/jam_photo/202202/07/75c43688-b342-44e5-b4be-38fec606fd6b.jpg"},{"title":"무쌍녀들의 워너비, 안소희의 ‘꾸안꾸’ 메이크업 전격 공개!","contents":"안소희가 ‘겟 레디 윗 미’에서 공개한 내추럴 무쌍 메이크업 루틴과 꿀템들을 모아 모아~.","link":"https://www.cosmopolitan.co.kr/article/63627","retrieved":1644225032740,"image":"https://image.jtbcplus.kr/data/contents/jam_photo/202202/07/fe9122e7-5daa-451e-a476-aae9cd10cbd6.jpg"},{"title":"블랙핑크 지수가 찍어준 동료 배우들의 인생샷 모음ZIP","contents":"박명수 버금간다는 연예계 프로(?) 사진작가 블랙핑크 지수?!","link":"https://www.cosmopolitan.co.kr/article/63625","retrieved":1644221567411,"image":"https://image.jtbcplus.kr/data/contents/jam_photo/202202/07/b58839ba-94c0-4cbb-a785-4f55566ca6c4.jpg"}]}