{"title":"코스모폴리탄 코리아 ─ 셀레브리티","url":"https://www.cosmopolitan.co.kr/celebs","favicon":"https://www.cosmopolitan.co.kr/favicon.ico","elements":[{"title":"이번엔 체대생 싸움이다! <대학체전: 소년선수촌> 관전포인트","contents":"&lt;피지컬:100&gt;, &lt;강철부대&gt; 거기에 &lt;스우파&gt;를 더해 꿀잼이라고.","link":"https://www.cosmopolitan.co.kr/article/84379","retrieved":1708648664515},{"title":"확신의 연예인 상! 엄마빠 꼭 닮은 스타 2세","contents":"이 집 DNA 미쳤다!","link":"https://www.cosmopolitan.co.kr/article/84364","retrieved":1708571440549},{"title":"AI 유명 유튜버 정체가 조정석?! 셀렙의 AI커버 열풍","contents":"요즘은 ‘AI 커버’도 ‘커버’한다.","link":"https://www.cosmopolitan.co.kr/article/84361","retrieved":1708571440556},{"title":"큰 거 온다! 티모시 샬라메·마룬5 등 내한 예정 셀럽 4","contents":"실물 영접은 어디서 할 수 있나요?","link":"https://www.cosmopolitan.co.kr/article/84334","retrieved":1708566034912},{"title":"청순 보스 라이즈  뮤비 속 여주의 정체는?","contents":"단발 머리가 잘 어울리는 그녀는 누구?","link":"https://www.cosmopolitan.co.kr/article/84278","retrieved":1708517731965},{"title":"숨겨진 끼 폭발? 연예계와 유튜브에 진출한 재벌 자녀 4","contents":"걸그룹부터 인턴 활동까지?","link":"https://www.cosmopolitan.co.kr/article/84269","retrieved":1708420185226},{"title":"나 얘 좋아하네…'첫사랑 재질' 성찬, 신유 극락 비주얼 모음집","contents":"할머니 지갑 속에서 발견한 아련한 첫사랑상이 이런 것?","link":"https://www.cosmopolitan.co.kr/article/84268","retrieved":1708398627313},{"title":"역대급 케미 예고? 아이유 x 탕웨이가 만났다!","contents":"2월 23일만 기다려요~.","link":"https://www.cosmopolitan.co.kr/article/84267","retrieved":1708319439761}]}