{"title":"코스모폴리탄 코리아 ─ 패션","url":"https://www.cosmopolitan.co.kr/fashion","favicon":"https://www.cosmopolitan.co.kr/favicon.ico","elements":[{"title":"배우 김민규와 오니츠카타이거의 기막힌 조우, SHADOW!","contents":"1980년대를 향한 아름다운 오마주, 오니츠카타이거의 AW 22 컬렉션 캠페인","link":"https://www.cosmopolitan.co.kr/article/67657","retrieved":1656580210182,"image":"https://image.jtbcplus.kr/data/contents/jam_photo/202206/30/848b43ab-80bf-4742-80b3-e3390bba4ac3.jpg"},{"title":"더워도 절대 포기 못해! 부츠 러버들을 위한 멋잘알 여름 부츠 스타일링 TIP","contents":"두아 리파부터 빅토리아 시크릿 엔젤 엘사 호스크까지 전부 있다니까?","link":"https://www.cosmopolitan.co.kr/article/67616","retrieved":1656572889968,"image":"https://image.jtbcplus.kr/data/contents/jam_photo/202206/29/b5ca3c38-19ce-4f8b-bc60-f3d23dd18be7.jpg"},{"title":"안유진·표예진 등 러블리하고 시크한 거 다 하는 셀럽들의 여름 긴팔 스타일링","contents":"여름 에어컨 바람과 햇빛으로부터 긴팔 패션 절대 지켜!","link":"https://www.cosmopolitan.co.kr/article/67615","retrieved":1656572889969,"image":"https://image.jtbcplus.kr/data/contents/jam_photo/202206/30/7256d0e0-bbf6-4cdd-8350-fe791504713d.jpg"},{"title":"볶아야 산다! 뷔·선미·천우희·한지민의 히피 펌 스타일링","contents":"화려한 컬러부터 브레이드 스타일, 헤어 액세서리까지, 올여름 헤어 트렌드는 맥시멀 그 자체! ...","link":"https://www.cosmopolitan.co.kr/article/67613","retrieved":1656569584297,"image":"https://image.jtbcplus.kr/data/contents/jam_photo/202206/30/c45f56fc-d33a-4a7c-bfa2-dce3114918bc.jpg"},{"title":"여름에 모자? 오히려 좋아~","contents":"라피아부터 버킷햇, 페도라까지 가보자고!","link":"https://www.cosmopolitan.co.kr/article/67612","retrieved":1656569584299,"image":"https://image.jtbcplus.kr/data/contents/jam_photo/202206/29/792bb78b-40e1-4ffc-aa4b-0918ce1dbaab.jpg"},{"title":"지금 바로 손민수 각? 아이유∙설현∙아이린의 같은 옷 다른 느낌!","contents":"올여름 유행하는 프린트 크롭트 티셔츠로 셀럽 룩 따라잡기","link":"https://www.cosmopolitan.co.kr/article/67605","retrieved":1656569584300,"image":"https://image.jtbcplus.kr/data/contents/jam_photo/202206/29/ba8e06c4-7dd0-4ebc-9fa4-c28ff2d759c0.jpg"},{"title":"아이돌 참 쉽죠? 헤어핀 하나면 여돌 재질 쌉가능","contents":"눈에서 꿀이 뚝뚝! 태연∙르세라핌∙엔믹스∙쏠의 헤어핀 스타일링","link":"https://www.cosmopolitan.co.kr/article/67585","retrieved":1656505136422,"image":"https://image.jtbcplus.kr/data/contents/jam_photo/202206/29/8acd1d0b-825c-4b50-a798-f36e5225fac7.jpg"},{"title":"여긴 몰랐지? 현아의 29금 타투 스팟","contents":"유교걸들 눈감아~ 타투 위치 고민 중이라면 소문난 타투좌 현아의 예를 참고할 것!","link":"https://www.cosmopolitan.co.kr/article/67574","retrieved":1656505136424,"image":"https://image.jtbcplus.kr/data/contents/jam_photo/202206/28/e5aca683-f236-44c8-94ab-be4bb453523e.jpg"}]}