{"title":"코스모폴리탄 코리아 ─ 패션","url":"https://www.cosmopolitan.co.kr/fashion","favicon":"https://www.cosmopolitan.co.kr/favicon.ico","elements":[{"title":"FREEDOM IN NY! 실험적인 패션 판타지 2023 F/W 뉴욕 패션 위크","contents":"변화무쌍한 패션계의 시각은 매 시즌 우리를 새로운 방향으로 이끈다. 2023 F/W 컬렉션의 가장...","link":"https://www.cosmopolitan.co.kr/article/76516","retrieved":1681052922347,"image":"https://image.jtbcplus.kr/data/contents/jam_photo/202304/07/1e0cf48e-35e9-485f-b785-1d8c5e1f780b.jpg"},{"title":"꽃’ 뮤비 속 지수가 입은 드레스 브랜드는?","contents":"글로벌 앰버서더인 디올 드레스부터 국내 디자이너브랜드까지!","link":"https://www.cosmopolitan.co.kr/article/76507","retrieved":1680991687149,"image":"https://image.jtbcplus.kr/data/contents/jam_photo/202304/07/e5b2cab3-b9a4-4b36-802d-a05ebaa8facb.jpg"},{"title":"MAMMA MIA! 참신한 아이디어로 가득찬 2023 F/W 밀라노 패션 위크","contents":"변화무쌍한 패션계의 시각은 매 시즌 우리를 새로운 방향으로 이끈다. 2023 F/W 컬렉션의 가장...","link":"https://www.cosmopolitan.co.kr/article/76497","retrieved":1680991687151,"image":"https://image.jtbcplus.kr/data/contents/jam_photo/202304/06/4ea3bc5e-4653-4a09-8492-f48a2f145715.jpg"},{"title":"트.잘.알 오셨다! 이사배의 데이 투 나잇 룩 최초 공개","contents":"올 봄에 뭐 입지? 고민이라면 드루와~","link":"https://www.cosmopolitan.co.kr/article/76482","retrieved":1680880127728,"image":"https://image.jtbcplus.kr/data/contents/jam_photo/202304/05/bf481f2f-9db2-49a9-bff2-b86295aa2faf.jpg"},{"title":"<피지컬:100>에서 눈동장을 쾅!찍은 출연진들이 말하는 '근짱'되는 법은?","contents":"갓피지컬을 가진 언니들이 핫하다, 핫해!  탄탄하고 건강한 신체로 미의 기준을 다시 세우며 넷...","link":"https://www.cosmopolitan.co.kr/article/76479","retrieved":1680880127729,"image":"https://image.jtbcplus.kr/data/contents/jam_photo/202304/05/d1200707-14a9-4536-ae91-68681c36a614.jpg"},{"title":"PAST & FUTURE! 과거와 현재의 앙상블 2023 F/W 파리 패션 위크","contents":"변화무쌍한 패션계의 시각은 매 시즌 우리를 새로운 방향으로 이끈다. 2023 F/W 컬렉션의 가장...","link":"https://www.cosmopolitan.co.kr/article/76304","retrieved":1680793746404,"image":"https://image.jtbcplus.kr/data/contents/jam_photo/202304/05/98b839b3-40a0-489c-a906-a1405b42c946.jpg"},{"title":"귀여운게 최고! 키덜트 패션의 세계","contents":"내 가방은 세일러문, 네 부츠는 아톰. 이런 걸 어떻게 착용하냐고? 보기만 해도 웃음이 터지는...","link":"https://www.cosmopolitan.co.kr/article/76302","retrieved":1680750573876,"image":"https://image.jtbcplus.kr/data/contents/jam_photo/202304/04/cde822f7-2470-496d-9e09-688c4bbd702f.jpg"},{"title":"KEEP COOL GO BRAID! 브레이드 헤어스타일링 6","contents":"제대로 꼬인 요즘 애들.","link":"https://www.cosmopolitan.co.kr/article/76223","retrieved":1680707420641,"image":"https://image.jtbcplus.kr/data/contents/jam_photo/202304/04/6f83de82-2a35-461d-bf2c-b73d625ea31f.jpg"},{"title":"멋쁨 폭발! <길복순> 전도연의 리즈 시절 패션 스타일은?","contents":"<div class=\"imgbox Thumb455\" style=\"background-image: url('https://image.jtbcplus.kr/data/contents/jam_photo/202304/03/fb643cd1-55c0-47ee-b7c4-6a826240f28f.jpg');\">\n            <a href=\"/article/76423\">\n                <img alt=\"\" src=\"\">\n            </a>\n        </div>\n<!--        <div class=\"imgbox\">-->\n<!--            <a href=\"/article/--><!--\">-->\n<!--                <img src=\"--><!--\" alt=\"--><!--\">-->\n<!--            </a>-->\n<!--        </div>-->\n        <div class=\"textbox\">\n                                <span class=\"menu\">\n                                    <a href=\"/article/76423\">\n                                        Celebrity Style                                    </a>\n                                </span>\n            <em class=\"title\">\n                <a href=\"/article/76423\">\n                    멋쁨 폭발! &lt;길복순&gt; 전도연의 리즈 시절 패션 스타일은?                </a>\n            </em>\n            <p class=\"excerpt\">이 언니, 멋있고 사랑스럽고 다 해~!</p>\n        </div>","link":"https://www.cosmopolitan.co.kr/article/76423","retrieved":1680664184505,"image":"https://image.jtbcplus.kr/data/contents/jam_photo/202304/03/fb643cd1-55c0-47ee-b7c4-6a826240f28f.jpg"},{"title":"“오늘부터 내 꿈은 너야.” 이도현이 반한 임지연의 사복 스타일은?","contents":"<div class=\"imgbox Thumb455\" style=\"background-image: url('https://image.jtbcplus.kr/data/contents/jam_photo/202304/03/67fa51af-8b10-4171-a9a4-0e01d138dc23.jpg');\">\n            <a href=\"/article/76418\">\n                <img alt=\"\" src=\"\">\n            </a>\n        </div>\n<!--        <div class=\"imgbox\">-->\n<!--            <a href=\"/article/--><!--\">-->\n<!--                <img src=\"--><!--\" alt=\"--><!--\">-->\n<!--            </a>-->\n<!--        </div>-->\n        <div class=\"textbox\">\n                                <span class=\"menu\">\n                                    <a href=\"/article/76418\">\n                                        Celebrity Style                                    </a>\n                                </span>\n            <em class=\"title\">\n                <a href=\"/article/76418\">\n                    “오늘부터 내 꿈은 너야.” 이도현이 반한 임지연의 사복 스타일은?                </a>\n            </em>\n            <p class=\"excerpt\">브라보, 박연진! 멋있다, 연진아! </p>\n        </div>","link":"https://www.cosmopolitan.co.kr/article/76418","retrieved":1681052922308,"image":"https://image.jtbcplus.kr/data/contents/jam_photo/202304/03/67fa51af-8b10-4171-a9a4-0e01d138dc23.jpg"},{"title":"STEP INTO SPRING! 봄 스커트 트렌드 따라잡기","contents":"<div class=\"imgbox Thumb455\" style=\"background-image: url('https://image.jtbcplus.kr/data/contents/jam_photo/202304/03/7faf74a6-47f9-4933-91c4-32d35f7b7827.jpg');\">\n            <a href=\"/article/76301\">\n                <img alt=\"\" src=\"\">\n            </a>\n        </div>\n<!--        <div class=\"imgbox\">-->\n<!--            <a href=\"/article/--><!--\">-->\n<!--                <img src=\"--><!--\" alt=\"--><!--\">-->\n<!--            </a>-->\n<!--        </div>-->\n        <div class=\"textbox\">\n                                <span class=\"menu\">\n                                    <a href=\"/article/76301\">\n                                        Trends                                    </a>\n                                </span>\n            <em class=\"title\">\n                <a href=\"/article/76301\">\n                    STEP INTO SPRING! 봄 스커트 트렌드 따라잡기                </a>\n            </em>\n            <p class=\"excerpt\">봄은 치맛자락을 타고. 우리를 설레게 만드는 스커트 트렌드 5가지.</p>\n        </div>","link":"https://www.cosmopolitan.co.kr/article/76301","retrieved":1681052922311,"image":"https://image.jtbcplus.kr/data/contents/jam_photo/202304/03/7faf74a6-47f9-4933-91c4-32d35f7b7827.jpg"},{"title":"BIG BAG IS BACK! 수납력 갑, 빅 백 전성시대","contents":"<div class=\"imgbox Thumb455\" style=\"background-image: url('https://image.jtbcplus.kr/data/contents/jam_photo/202304/02/0e9955f3-3443-4f33-a791-574652071a17.jpg');\">\n            <a href=\"/article/76300\">\n                <img alt=\"\" src=\"\">\n            </a>\n        </div>\n<!--        <div class=\"imgbox\">-->\n<!--            <a href=\"/article/--><!--\">-->\n<!--                <img src=\"--><!--\" alt=\"--><!--\">-->\n<!--            </a>-->\n<!--        </div>-->\n        <div class=\"textbox\">\n                                <span class=\"menu\">\n                                    <a href=\"/article/76300\">\n                                        Shopping                                    </a>\n                                </span>\n            <em class=\"title\">\n                <a href=\"/article/76300\">\n                    BIG BAG IS BACK! 수납력 갑, 빅 백 전성시대                </a>\n            </em>\n            <p class=\"excerpt\">지금 알아야 할 이달의 핫 이슈.</p>\n        </div>","link":"https://www.cosmopolitan.co.kr/article/76300","retrieved":1681052922332,"image":"https://image.jtbcplus.kr/data/contents/jam_photo/202304/02/0e9955f3-3443-4f33-a791-574652071a17.jpg"},{"title":"봄 맞이 인테리어 각? 봄기운 가득 품은 홈 아이템8","contents":"<div class=\"imgbox Thumb455\" style=\"background-image: url('https://image.jtbcplus.kr/data/contents/jam_photo/202304/01/9e0c13a8-01ad-4078-9909-81a076ded175.jpg');\">\n            <a href=\"/article/76205\">\n                <img alt=\"\" src=\"\">\n            </a>\n        </div>\n<!--        <div class=\"imgbox\">-->\n<!--            <a href=\"/article/--><!--\">-->\n<!--                <img src=\"--><!--\" alt=\"--><!--\">-->\n<!--            </a>-->\n<!--        </div>-->\n        <div class=\"textbox\">\n                                <span class=\"menu\">\n                                    <a href=\"/article/76205\">\n                                        Accessories                                    </a>\n                                </span>\n            <em class=\"title\">\n                <a href=\"/article/76205\">\n                    봄 맞이 인테리어 각? 봄기운 가득 품은 홈 아이템8                </a>\n            </em>\n            <p class=\"excerpt\">지금 알아야 할 이달의 핫 이슈.</p>\n        </div>","link":"https://www.cosmopolitan.co.kr/article/76205","retrieved":1681052922334,"image":"https://image.jtbcplus.kr/data/contents/jam_photo/202304/01/9e0c13a8-01ad-4078-9909-81a076ded175.jpg"},{"title":"COSMO HOT! 코스모가 픽한 4월의 아이템은?","contents":"<div class=\"imgbox Thumb455\" style=\"background-image: url('https://image.jtbcplus.kr/data/contents/jam_photo/202304/01/e39af5bb-05b7-4fbb-afb0-d569ca8c3172.jpg');\">\n            <a href=\"/article/76394\">\n                <img alt=\"\" src=\"\">\n            </a>\n        </div>\n<!--        <div class=\"imgbox\">-->\n<!--            <a href=\"/article/--><!--\">-->\n<!--                <img src=\"--><!--\" alt=\"--><!--\">-->\n<!--            </a>-->\n<!--        </div>-->\n        <div class=\"textbox\">\n                                <span class=\"menu\">\n                                    <a href=\"/article/76394\">\n                                        Shopping                                    </a>\n                                </span>\n            <em class=\"title\">\n                <a href=\"/article/76394\">\n                    COSMO HOT! 코스모가 픽한 4월의 아이템은?                </a>\n            </em>\n            <p class=\"excerpt\">코스모가 픽한 4월의 아이템.</p>\n        </div>","link":"https://www.cosmopolitan.co.kr/article/76394","retrieved":1681052922335,"image":"https://image.jtbcplus.kr/data/contents/jam_photo/202304/01/e39af5bb-05b7-4fbb-afb0-d569ca8c3172.jpg"},{"title":"대체불가 이효리","contents":"<div class=\"imgbox Thumb455\" style=\"background-image: url('https://image.jtbcplus.kr/data/contents/jam_photo/202303/29/4985ddae-1706-4789-beb7-b304dc59da4f.jpg');\">\n            <a href=\"/article/76251\">\n                <img alt=\"\" src=\"\">\n            </a>\n        </div>\n<!--        <div class=\"imgbox\">-->\n<!--            <a href=\"/article/--><!--\">-->\n<!--                <img src=\"--><!--\" alt=\"--><!--\">-->\n<!--            </a>-->\n<!--        </div>-->\n        <div class=\"textbox\">\n                                <span class=\"menu\">\n                                    <a href=\"/article/76251\">\n                                        Celeb News                                    </a>\n                                </span>\n            <em class=\"title\">\n                <a href=\"/article/76251\">\n                    대체불가 이효리                </a>\n            </em>\n            <p class=\"excerpt\">지금 이대로 좋아. 여유와 쿨함이 느껴지는 이효리와 쟈딕앤볼테르의 애티튜드.</p>\n        </div>","link":"https://www.cosmopolitan.co.kr/article/76251","retrieved":1681052922340,"image":"https://image.jtbcplus.kr/data/contents/jam_photo/202303/29/4985ddae-1706-4789-beb7-b304dc59da4f.jpg"},{"title":"많을수록 좋아! ‘다다익선 포켓’ 패션에 빠진 셀렙은?","contents":"<div class=\"imgbox Thumb455\" style=\"background-image: url('https://image.jtbcplus.kr/data/contents/jam_photo/202303/27/2c5ba593-44f3-4838-ba86-b4cadcadc224.jpg');\">\n                <a href=\"/article/76163\">\n                    <img alt=\"\" src=\"\">\n                </a>\n            </div>\n<!--            <div class=\"imgbox\">-->\n<!--                <a href=\"/article/--><!--\">-->\n<!--                    <img src=\"--><!--\" alt=\"--><!--\">-->\n<!--                </a>-->\n<!--            </div>-->\n            <div class=\"textbox\">\n                                <span class=\"menu\">\n                                    <a href=\"/article/76163\">\n                                        Celebrity Style                                    </a>\n                                </span>\n                <em class=\"title\">\n                    <a href=\"/article/76163\">\n                        많을수록 좋아! ‘다다익선 포켓’ 패션에 빠진 셀렙은?                     </a>\n                </em>\n                <p class=\"excerpt\">어디에 넣었는지 까먹을 수 있으니 주의! </p>\n            </div>","link":"https://www.cosmopolitan.co.kr/article/76163","retrieved":1681052922343,"image":"https://image.jtbcplus.kr/data/contents/jam_photo/202303/27/2c5ba593-44f3-4838-ba86-b4cadcadc224.jpg"},{"title":"샤넬부터 셀린느까지! 명품 테니스 백 가격은 얼마?","contents":"<div class=\"imgbox Thumb455\" style=\"background-image: url('https://image.jtbcplus.kr/data/contents/jam_photo/202303/27/4a4bf1af-c00a-48ff-a02f-54ce2cf2cbbd.jpg');\">\n                <a href=\"/article/76162\">\n                    <img alt=\"\" src=\"\">\n                </a>\n            </div>\n<!--            <div class=\"imgbox\">-->\n<!--                <a href=\"/article/--><!--\">-->\n<!--                    <img src=\"--><!--\" alt=\"--><!--\">-->\n<!--                </a>-->\n<!--            </div>-->\n            <div class=\"textbox\">\n                                <span class=\"menu\">\n                                    <a href=\"/article/76162\">\n                                        Shopping                                    </a>\n                                </span>\n                <em class=\"title\">\n                    <a href=\"/article/76162\">\n                        샤넬부터 셀린느까지! 명품 테니스 백 가격은 얼마?                    </a>\n                </em>\n                <p class=\"excerpt\">테니스 백이 이렇게 예뻐도 되는겁니까!</p>\n            </div>","link":"https://www.cosmopolitan.co.kr/article/76162","retrieved":1681052922369,"image":"https://image.jtbcplus.kr/data/contents/jam_photo/202303/27/4a4bf1af-c00a-48ff-a02f-54ce2cf2cbbd.jpg"},{"title":"패피들 사이에서 대세라는 아톰부츠! 전소미∙홍은채 등 연예인 착샷 4","contents":"<div class=\"imgbox Thumb455\" style=\"background-image: url('https://image.jtbcplus.kr/data/contents/jam_photo/202303/23/c8dda525-e37d-41ff-8fd6-b06e3d9b0764.jpg');\">\n                <a href=\"/article/76061\">\n                    <img alt=\"\" src=\"\">\n                </a>\n            </div>\n<!--            <div class=\"imgbox\">-->\n<!--                <a href=\"/article/--><!--\">-->\n<!--                    <img src=\"--><!--\" alt=\"--><!--\">-->\n<!--                </a>-->\n<!--            </div>-->\n            <div class=\"textbox\">\n                                <span class=\"menu\">\n                                    <a href=\"/article/76061\">\n                                        Celebrity Style                                    </a>\n                                </span>\n                <em class=\"title\">\n                    <a href=\"/article/76061\">\n                        패피들 사이에서 대세라는 아톰부츠! 전소미∙홍은채 등 연예인 착샷 4                     </a>\n                </em>\n                <p class=\"excerpt\">이게 정말 유행이라고?! </p>\n            </div>","link":"https://www.cosmopolitan.co.kr/article/76061","retrieved":1681052922371,"image":"https://image.jtbcplus.kr/data/contents/jam_photo/202303/23/c8dda525-e37d-41ff-8fd6-b06e3d9b0764.jpg"},{"title":"임지연∙수영∙김나영 등 셀럽들의 청청패션 코디 5","contents":"<div class=\"imgbox Thumb455\" style=\"background-image: url('https://image.jtbcplus.kr/data/contents/jam_photo/202303/23/e2ff9dc6-7601-4745-8bdd-d39dfc0776fc.jpg');\">\n                <a href=\"/article/76060\">\n                    <img alt=\"\" src=\"\">\n                </a>\n            </div>\n<!--            <div class=\"imgbox\">-->\n<!--                <a href=\"/article/--><!--\">-->\n<!--                    <img src=\"--><!--\" alt=\"--><!--\">-->\n<!--                </a>-->\n<!--            </div>-->\n            <div class=\"textbox\">\n                                <span class=\"menu\">\n                                    <a href=\"/article/76060\">\n                                        Celebrity Style                                    </a>\n                                </span>\n                <em class=\"title\">\n                    <a href=\"/article/76060\">\n                        임지연∙수영∙김나영 등 셀럽들의 청청패션 코디 5                    </a>\n                </em>\n                <p class=\"excerpt\">올 봄 트렌드인 청청 데님 패션, 셀럽들은 어떻게 입었을까? </p>\n            </div>","link":"https://www.cosmopolitan.co.kr/article/76060","retrieved":1681052922373,"image":"https://image.jtbcplus.kr/data/contents/jam_photo/202303/23/e2ff9dc6-7601-4745-8bdd-d39dfc0776fc.jpg"},{"title":"기은세가 피워낸 봄","contents":"<div class=\"imgbox Thumb455\" style=\"background-image: url('https://image.jtbcplus.kr/data/contents/jam_photo/202303/21/648aa530-d74a-488b-b72a-985b44bec462.jpg');\">\n                <a href=\"/article/75933\">\n                    <img alt=\"\" src=\"\">\n                </a>\n            </div>\n<!--            <div class=\"imgbox\">-->\n<!--                <a href=\"/article/--><!--\">-->\n<!--                    <img src=\"--><!--\" alt=\"--><!--\">-->\n<!--                </a>-->\n<!--            </div>-->\n            <div class=\"textbox\">\n                                <span class=\"menu\">\n                                    <a href=\"/article/75933\">\n                                        Trends                                    </a>\n                                </span>\n                <em class=\"title\">\n                    <a href=\"/article/75933\">\n                        기은세가 피워낸 봄                    </a>\n                </em>\n                <p class=\"excerpt\">셀렙샵 에디션과 함께한 기은세의 스프링 룩.</p>\n            </div>","link":"https://www.cosmopolitan.co.kr/article/75933","retrieved":1681052922375,"image":"https://image.jtbcplus.kr/data/contents/jam_photo/202303/21/648aa530-d74a-488b-b72a-985b44bec462.jpg"},{"title":"올봄엔 데님 재킷? 스타일리시한 셀럽들의 데님 재킷 스타일링","contents":"<div class=\"imgbox Thumb455\" style=\"background-image: url('https://image.jtbcplus.kr/data/contents/jam_photo/202303/21/a1146a66-ef15-471d-8f23-967529b24f2b.jpg');\">\n                <a href=\"/article/75989\">\n                    <img alt=\"\" src=\"\">\n                </a>\n            </div>\n<!--            <div class=\"imgbox\">-->\n<!--                <a href=\"/article/--><!--\">-->\n<!--                    <img src=\"--><!--\" alt=\"--><!--\">-->\n<!--                </a>-->\n<!--            </div>-->\n            <div class=\"textbox\">\n                                <span class=\"menu\">\n                                    <a href=\"/article/75989\">\n                                        Celebrity Style                                    </a>\n                                </span>\n                <em class=\"title\">\n                    <a href=\"/article/75989\">\n                        올봄엔 데님 재킷? 스타일리시한 셀럽들의 데님 재킷 스타일링                     </a>\n                </em>\n                <p class=\"excerpt\">“캐주얼한데, 힙해!” 셀럽들의 인스타그램에서 찾은 데님 재킷 스타일링. </p>\n            </div>","link":"https://www.cosmopolitan.co.kr/article/75989","retrieved":1681052922394,"image":"https://image.jtbcplus.kr/data/contents/jam_photo/202303/21/a1146a66-ef15-471d-8f23-967529b24f2b.jpg"}]}