{"title":"코스모폴리탄 코리아 ─ 라이프","url":"https://www.cosmopolitan.co.kr/life","favicon":"https://www.cosmopolitan.co.kr/favicon.ico","elements":[{"title":"착한데 제품력까지? 환경 보호에 앞장서는 뷰티 브랜드 모음ZIP","contents":"<div class=\"imgbox Thumb455\" style=\"background-image: url('https://image.jtbcplus.kr/data/contents/jam_photo/202204/10/1c75fe48-c6fd-4025-83ac-81bdef123d21.jpg');\">\n                                <a href=\"/article/65397\">\n                                    <img alt=\"\" src=\"\">\n                                </a>\n                            </div>\n                            <!-- <div class=\"imgbox\">\n                                <a href=\"/article/\">\n                                    <img src=\"\" alt=\"\">\n                                </a>\n                            </div> -->\n                            <div class=\"textbox\">\n                                <span class=\"menu\">\n                                    <a href=\"/article/65397\">\n                                        Society Matters                                    </a>\n                                </span>\n                                <em class=\"title\">\n                                    <a href=\"/article/65397\">\n                                        착한데 제품력까지? 환경 보호에 앞장서는 뷰티 브랜드 모음ZIP                                    </a>\n                                </em>\n                                <p class=\"excerpt\">건강한 지구를 지속 가능하게 하리라는 다짐을 지속 가능하게 만드는 착한 에코 브랜드들.</p>\n                            </div>","link":"https://www.cosmopolitan.co.kr/article/65397","retrieved":1649648676386,"image":"https://image.jtbcplus.kr/data/contents/jam_photo/202204/10/1c75fe48-c6fd-4025-83ac-81bdef123d21.jpg"},{"title":"벚꽃은 편하게 호텔에서! 호캉스에 벚꽃을 더한 여행 숙소는 여기로!","contents":"<div class=\"imgbox Thumb455\" style=\"background-image: url('https://image.jtbcplus.kr/data/contents/jam_photo/202204/07/816efb9f-a824-4471-a48c-bc98aa4dfd57.jpg');\">\n                                <a href=\"/article/65342\">\n                                    <img alt=\"\" src=\"\">\n                                </a>\n                            </div>\n                            <!-- <div class=\"imgbox\">\n                                <a href=\"/article/\">\n                                    <img src=\"\" alt=\"\">\n                                </a>\n                            </div> -->\n                            <div class=\"textbox\">\n                                <span class=\"menu\">\n                                    <a href=\"/article/65342\">\n                                        Travel                                    </a>\n                                </span>\n                                <em class=\"title\">\n                                    <a href=\"/article/65342\">\n                                        벚꽃은 편하게 호텔에서! 호캉스에 벚꽃을 더한 여행 숙소는 여기로!                                    </a>\n                                </em>\n                                <p class=\"excerpt\">벚캉스 전문 호텔 4</p>\n                            </div>","link":"https://www.cosmopolitan.co.kr/article/65342","retrieved":1649648676386,"image":"https://image.jtbcplus.kr/data/contents/jam_photo/202204/07/816efb9f-a824-4471-a48c-bc98aa4dfd57.jpg"},{"title":"빅뱅 4년만에 컴백! 탑은 YG를 떠난다는데?","contents":"<div class=\"imgbox Thumb455\" style=\"background-image: url('https://image.jtbcplus.kr/data/contents/jam_photo/202204/07/1a917a18-5db2-4deb-81d3-f01d380564e3.jpg');\">\n                                <a href=\"/article/65340\">\n                                    <img alt=\"\" src=\"\">\n                                </a>\n                            </div>\n                            <!-- <div class=\"imgbox\">\n                                <a href=\"/article/\">\n                                    <img src=\"\" alt=\"\">\n                                </a>\n                            </div> -->\n                            <div class=\"textbox\">\n                                <span class=\"menu\">\n                                    <a href=\"/article/65340\">\n                                        Celeb News                                    </a>\n                                </span>\n                                <em class=\"title\">\n                                    <a href=\"/article/65340\">\n                                        빅뱅 4년만에 컴백! 탑은 YG를 떠난다는데?                                     </a>\n                                </em>\n                                <p class=\"excerpt\">웃어야 돼? 울어야 돼? </p>\n                            </div>","link":"https://www.cosmopolitan.co.kr/article/65340","retrieved":1649648676397,"image":"https://image.jtbcplus.kr/data/contents/jam_photo/202204/07/1a917a18-5db2-4deb-81d3-f01d380564e3.jpg"},{"title":"알로하! 드디어 하와이 여행 갈 수 있다고?","contents":"<div class=\"imgbox Thumb455\" style=\"background-image: url('https://image.jtbcplus.kr/data/contents/jam_photo/202204/11/3ab5b07d-e039-4b90-9585-11fa6fd380a9.jpg');\">\n                                <a href=\"/article/65338\">\n                                    <img alt=\"\" src=\"\">\n                                </a>\n                            </div>\n                            <!-- <div class=\"imgbox\">\n                                <a href=\"/article/\">\n                                    <img src=\"\" alt=\"\">\n                                </a>\n                            </div> -->\n                            <div class=\"textbox\">\n                                <span class=\"menu\">\n                                    <a href=\"/article/65338\">\n                                        Travel                                    </a>\n                                </span>\n                                <em class=\"title\">\n                                    <a href=\"/article/65338\">\n                                        알로하! 드디어 하와이 여행 갈 수 있다고?                                    </a>\n                                </em>\n                                <p class=\"excerpt\">김나영도 간 하와이, 어떻게 가는지 한 번에 정리해 드림</p>\n                            </div>","link":"https://www.cosmopolitan.co.kr/article/65338","retrieved":1649648676400,"image":"https://image.jtbcplus.kr/data/contents/jam_photo/202204/11/3ab5b07d-e039-4b90-9585-11fa6fd380a9.jpg"},{"title":"실외 마스크 착용 의무 해제되면 나는 OOO할 것이다?","contents":"<div class=\"imgbox Thumb455\" style=\"background-image: url('https://image.jtbcplus.kr/data/contents/jam_photo/202204/11/7f65d5d2-800a-4b6f-85e1-e5d1f2638452.jpg');\">\n                                <a href=\"/article/65331\">\n                                    <img alt=\"\" src=\"\">\n                                </a>\n                            </div>\n<!--                            <div class=\"imgbox\">-->\n<!--                                <a href=\"/article/--><!--\">-->\n<!--                                    <img src=\"--><!--\" alt=\"--><!--\">-->\n<!--                                </a>-->\n<!--                            </div>-->\n                            <div class=\"textbox\">\n                                <span class=\"menu\">\n                                    <a href=\"/article/65331\">\n                                        Culture                                    </a>\n                                </span>\n                                <em class=\"title\">\n                                    <a href=\"/article/65331\">\n                                        실외 마스크 착용 의무 해제되면 나는 OOO할 것이다?                                    </a>\n                                </em>\n                                <p class=\"excerpt\">마스크, 드디어 벗나요?! 실외 마스크 착용 의무화가 해제될 가능성이 커지면서 기대와 우려가 ...</p>\n                            </div>","link":"https://www.cosmopolitan.co.kr/article/65331","retrieved":1649521088209,"image":"https://image.jtbcplus.kr/data/contents/jam_photo/202204/11/7f65d5d2-800a-4b6f-85e1-e5d1f2638452.jpg"},{"title":"사주로 보는 속궁합? 역술가가 알려주는 숨은 찰떡궁합 찾기!","contents":"<div class=\"imgbox Thumb455\" style=\"background-image: url('https://image.jtbcplus.kr/data/contents/jam_photo/202204/07/5c813522-1e59-4e88-9865-946d0c066cd9.jpg');\">\n                                <a href=\"/article/65326\">\n                                    <img alt=\"\" src=\"\">\n                                </a>\n                            </div>\n<!--                            <div class=\"imgbox\">-->\n<!--                                <a href=\"/article/--><!--\">-->\n<!--                                    <img src=\"--><!--\" alt=\"--><!--\">-->\n<!--                                </a>-->\n<!--                            </div>-->\n                            <div class=\"textbox\">\n                                <span class=\"menu\">\n                                    <a href=\"/article/65326\">\n                                        Trends                                    </a>\n                                </span>\n                                <em class=\"title\">\n                                    <a href=\"/article/65326\">\n                                        사주로 보는 속궁합? 역술가가 알려주는 숨은 찰떡궁합 찾기!                                    </a>\n                                </em>\n                                <p class=\"excerpt\">어릴 적 부모님에게 받은 사랑을 남자에게 갈구하는 ‘아기녀’부터 아내의 말 한마디에 경기를 ...</p>\n                            </div>","link":"https://www.cosmopolitan.co.kr/article/65326","retrieved":1649521088210,"image":"https://image.jtbcplus.kr/data/contents/jam_photo/202204/07/5c813522-1e59-4e88-9865-946d0c066cd9.jpg"},{"title":"석촌호수에 가면? 벨리곰도 보고, 벚꽃도 보고, 맛있는 것도 먹을 수 있는 찐 데이트 코스","contents":"<div class=\"imgbox Thumb455\" style=\"background-image: url('https://image.jtbcplus.kr/data/contents/jam_photo/202204/06/8eb8f6f7-1874-4b8f-b53e-3c324a2b26d4.jpg');\">\n                                <a href=\"/article/65297\">\n                                    <img alt=\"\" src=\"\">\n                                </a>\n                            </div>\n<!--                            <div class=\"imgbox\">-->\n<!--                                <a href=\"/article/--><!--\">-->\n<!--                                    <img src=\"--><!--\" alt=\"--><!--\">-->\n<!--                                </a>-->\n<!--                            </div>-->\n                            <div class=\"textbox\">\n                                <span class=\"menu\">\n                                    <a href=\"/article/65297\">\n                                        Place                                    </a>\n                                </span>\n                                <em class=\"title\">\n                                    <a href=\"/article/65297\">\n                                        석촌호수에 가면? 벨리곰도 보고, 벚꽃도 보고, 맛있는 것도 먹을 수 있는 찐 데이트 코스                                    </a>\n                                </em>\n                                <p class=\"excerpt\">데이트 코스 완전 격파. 맛집까지 모두 정리해드림.zip</p>\n                            </div>","link":"https://www.cosmopolitan.co.kr/article/65297","retrieved":1649315828334,"image":"https://image.jtbcplus.kr/data/contents/jam_photo/202204/06/8eb8f6f7-1874-4b8f-b53e-3c324a2b26d4.jpg"},{"title":"지긋지긋하지만 다시 사랑한다 말할까?","contents":"<div class=\"imgbox Thumb455\" style=\"background-image: url('https://image.jtbcplus.kr/data/contents/jam_photo/202204/06/8e46a425-ef4d-4bd1-96d2-1088205a490a.jpg');\">\n                                <a href=\"/article/65280\">\n                                    <img alt=\"\" src=\"\">\n                                </a>\n                            </div>\n<!--                            <div class=\"imgbox\">-->\n<!--                                <a href=\"/article/--><!--\">-->\n<!--                                    <img src=\"--><!--\" alt=\"--><!--\">-->\n<!--                                </a>-->\n<!--                            </div>-->\n                            <div class=\"textbox\">\n                                <span class=\"menu\">\n                                    <a href=\"/article/65280\">\n                                        Society Matters                                    </a>\n                                </span>\n                                <em class=\"title\">\n                                    <a href=\"/article/65280\">\n                                        지긋지긋하지만 다시 사랑한다 말할까?                                    </a>\n                                </em>\n                                <p class=\"excerpt\">‘그저 그런 사랑한 거 아니고, 그저 그런 이별한 거 아닌’ 최웅과 국연수의 여름을 소환한 ...</p>\n                            </div>","link":"https://www.cosmopolitan.co.kr/article/65280","retrieved":1649315828335,"image":"https://image.jtbcplus.kr/data/contents/jam_photo/202204/06/8e46a425-ef4d-4bd1-96d2-1088205a490a.jpg"}]}